qbizdataraven/__init__.py
qbizdataraven/common.py
qbizdataraven/connections.py
qbizdataraven/data_quality_operators.py
qbizdataraven/exception_handling.py
qbizdataraven/log.py
qbizdataraven/measures.py
qbizdataraven/operations.py
qbizdataraven/test_logic.py
qbizdataraven/tests.py
qbizdataraven/csv/__init__.py
qbizdataraven/csv/operations.py
qbizdataraven/csv/reducers.py
qbizdataraven/sql/__init__.py
qbizdataraven/sql/core.py
qbizdataraven/sql/helpers.py
qbizdataraven/sql/measure_logic.py
qbizdataraven/sql/operations.py
qbiz_data_raven-0.1rc1.dist-info/METADATA
qbiz_data_raven-0.1rc1.dist-info/WHEEL
qbiz_data_raven-0.1rc1.dist-info/top_level.txt
qbiz_data_raven-0.1rc1.dist-info/RECORD
