Metadata-Version: 2.1
Name: qbiz-data-raven
Version: 0.1rc1
Summary: A Python framework for building data quality tests
Home-page: https://github.com/Qbizinc/qbiz-data-raven
Author: Alex Broley
Author-email: alex@qbizinc.com
License: UNKNOWN
Platform: UNKNOWN
Classifier: Programming Language :: Python :: 3
Classifier: License :: OSI Approved :: MIT License
Classifier: Operating System :: OS Independent
Requires-Python: >=3.6
Requires-Dist: sqlalchemy (>=1.3.19)
Requires-Dist: psycopg2-binary
Requires-Dist: pymysql
